approzium/__init__.py
approzium/_authenticator.py
approzium/_iam.py
approzium/_misc.py
approzium/_mysql/__init__.py
approzium/_postgres/__init__.py
approzium/_postgres/scram.py
approzium/_protos/authenticator_pb2.py
approzium/_protos/authenticator_pb2_grpc.py
approzium/asyncpg/__init__.py
approzium/asyncpg/_asyncpg_connect.py
approzium/asyncpg/pool.py
approzium/mysql/__init__.py
approzium/mysql/connector/__init__.py
approzium/mysql/connector/_connect.py
approzium/mysql/connector/pooling.py
approzium/opentelemetry/__init__.py
approzium/psycopg2/__init__.py
approzium/psycopg2/_psycopg2_connect.py
approzium/psycopg2/_psycopg2_ctypes.py
approzium/psycopg2/pool.py
approzium/pymysql/__init__.py
approzium/pymysql/_connect.py
approzium-0.2.4.dist-info/WHEEL
approzium-0.2.4.dist-info/METADATA
approzium-0.2.4.dist-info/RECORD
